odoo10_addon_website_sale_hide_price-10.0.1.0.0-py2.7-nspkg.pth
odoo/addons/website_sale_hide_price/README.rst
odoo/addons/website_sale_hide_price/__init__.py
odoo/addons/website_sale_hide_price/__manifest__.py
odoo/addons/website_sale_hide_price/i18n/es.po
odoo/addons/website_sale_hide_price/models/__init__.py
odoo/addons/website_sale_hide_price/models/res_partner.py
odoo/addons/website_sale_hide_price/models/website.py
odoo/addons/website_sale_hide_price/views/partner_view.xml
odoo/addons/website_sale_hide_price/views/website_sale_template.xml
odoo10_addon_website_sale_hide_price-10.0.1.0.0.dist-info/DESCRIPTION.rst
odoo10_addon_website_sale_hide_price-10.0.1.0.0.dist-info/METADATA
odoo10_addon_website_sale_hide_price-10.0.1.0.0.dist-info/RECORD
odoo10_addon_website_sale_hide_price-10.0.1.0.0.dist-info/WHEEL
odoo10_addon_website_sale_hide_price-10.0.1.0.0.dist-info/metadata.json
odoo10_addon_website_sale_hide_price-10.0.1.0.0.dist-info/namespace_packages.txt
odoo10_addon_website_sale_hide_price-10.0.1.0.0.dist-info/top_level.txt
